fairyfly/__init__.py
fairyfly/__main__.py
fairyfly/_base.py
fairyfly/_lockable.py
fairyfly/boundary.py
fairyfly/checkdup.py
fairyfly/colorobj.py
fairyfly/config.json
fairyfly/config.py
fairyfly/dictutil.py
fairyfly/extensionutil.py
fairyfly/logutil.py
fairyfly/model.py
fairyfly/properties.py
fairyfly/search.py
fairyfly/shape.py
fairyfly/typing.py
fairyfly/units.py
fairyfly/cli/__init__.py
fairyfly/cli/setconfig.py
fairyfly/writer/__init__.py
fairyfly/writer/boundary.py
fairyfly/writer/model.py
fairyfly/writer/shape.py
fairyfly_core-0.2.12.dist-info/licenses/LICENSE
fairyfly_core-0.2.12.dist-info/METADATA
fairyfly_core-0.2.12.dist-info/WHEEL
fairyfly_core-0.2.12.dist-info/entry_points.txt
fairyfly_core-0.2.12.dist-info/top_level.txt
fairyfly_core-0.2.12.dist-info/RECORD
